exporter/__init__.py
exporter/console_script.py
exporter/constants.py
exporter/exceptions.py
exporter/exporter.py
exporter/helper.py
exporter/image_exporter.py
exporter/monkey_patch.py
exporter-0.0.4.dist-info/LICENSE
exporter-0.0.4.dist-info/METADATA
exporter-0.0.4.dist-info/WHEEL
exporter-0.0.4.dist-info/entry_points.txt
exporter-0.0.4.dist-info/top_level.txt
exporter-0.0.4.dist-info/RECORD
